{"AED":{"code":"AED","title":"United Arab Emirates Dirham","symbol":"AED","native":"\u062f.\u0625.\u200f","thousands_sep":",","decimal_sep":".","symbol_left":true,"space_between":true,"exp":2,"min_amount":"367","max_amount":"3672850"},"AFN":{"code":"AFN","title":"Afghan Afghani","symbol":"AFN","native":"\u060b","thousands_sep":",","decimal_sep":".","symbol_left":true,"space_between":false,"exp":2,"min_amount":"7824","max_amount":"78249957"},"ALL":{"code":"ALL","title":"Albanian Lek","symbol":"ALL","native":"Lek","thousands_sep":".","decimal_sep":",","symbol_left":false,"space_between":false,"exp":2,"min_amount":"11104","max_amount":"111049596"},"AMD":{"code":"AMD","title":"Armenian Dram","symbol":"AMD","native":"\u0564\u0580.","thousands_sep":",","decimal_sep":".","symbol_left":false,"space_between":true,"exp":2,"min_amount":"47757","max_amount":"477570133"},"ARS":{"code":"ARS","title":"Argentine Peso","symbol":"ARS","native":"$","thousands_sep":".","decimal_sep":",","symbol_left":true,"space_between":true,"exp":2,"min_amount":"5968","max_amount":"59689414"},"AUD":{"code":"AUD","title":"Australian Dollar","symbol":"AU$","native":"$","thousands_sep":",","decimal_sep":".","symbol_left":true,"space_between":false,"exp":2,"min_amount":"146","max_amount":"1467555"},"AZN":{"code":"AZN","title":"Azerbaijani Manat","symbol":"AZN","native":"\u043c\u0430\u043d.","thousands_sep":"\u00a0","decimal_sep":",","symbol_left":false,"space_between":true,"exp":2,"min_amount":"169","max_amount":"1697666"},"BAM":{"code":"BAM","title":"Bosnia & Herzegovina Convertible Mark","symbol":"BAM","native":"KM","thousands_sep":".","decimal_sep":",","symbol_left":false,"space_between":true,"exp":2,"min_amount":"177","max_amount":"1773159"},"BDT":{"code":"BDT","title":"Bangladeshi Taka","symbol":"BDT","native":"\u09f3","thousands_sep":",","decimal_sep":".","symbol_left":true,"space_between":true,"exp":2,"min_amount":"8484","max_amount":"84843880"},"BGN":{"code":"BGN","title":"Bulgarian Lev","symbol":"BGN","native":"\u043b\u0432.","thousands_sep":"\u00a0","decimal_sep":",","symbol_left":false,"space_between":true,"exp":2,"min_amount":"176","max_amount":"1769731"},"BND":{"code":"BND","title":"Brunei Dollar","symbol":"BND","native":"$","thousands_sep":".","decimal_sep":",","symbol_left":true,"space_between":false,"exp":2,"min_amount":"136","max_amount":"1361716"},"BOB":{"code":"BOB","title":"Bolivian Boliviano","symbol":"BOB","native":"Bs","thousands_sep":".","decimal_sep":",","symbol_left":true,"space_between":true,"exp":2,"min_amount":"691","max_amount":"6915915"},"BRL":{"code":"BRL","title":"Brazilian Real","symbol":"R$","native":"R$","thousands_sep":".","decimal_sep":",","symbol_left":true,"space_between":true,"exp":2,"min_amount":"419","max_amount":"4196199"},"CAD":{"code":"CAD","title":"Canadian Dollar","symbol":"CA$","native":"$","thousands_sep":",","decimal_sep":".","symbol_left":true,"space_between":false,"exp":2,"min_amount":"132","max_amount":"1322045"},"CHF":{"code":"CHF","title":"Swiss Franc","symbol":"CHF","native":"CHF","thousands_sep":"'","decimal_sep":".","symbol_left":false,"space_between":true,"exp":2,"min_amount":"98","max_amount":"989630"},"CLP":{"code":"CLP","title":"Chilean Peso","symbol":"CLP","native":"$","thousands_sep":".","decimal_sep":",","symbol_left":true,"space_between":true,"exp":0,"min_amount":"776","max_amount":"7766935"},"CNY":{"code":"CNY","title":"Chinese Renminbi Yuan","symbol":"CN\u00a5","native":"CN\u00a5","thousands_sep":",","decimal_sep":".","symbol_left":true,"space_between":false,"exp":2,"min_amount":"700","max_amount":"7008395"},"COP":{"code":"COP","title":"Colombian Peso","symbol":"COP","native":"$","thousands_sep":".","decimal_sep":",","symbol_left":true,"space_between":true,"exp":2,"min_amount":"343600","max_amount":"3436000000"},"CRC":{"code":"CRC","title":"Costa Rican Col\u00f3n","symbol":"CRC","native":"\u20a1","thousands_sep":".","decimal_sep":",","symbol_left":true,"space_between":false,"exp":2,"min_amount":"58179","max_amount":"581793620"},"CZK":{"code":"CZK","title":"Czech Koruna","symbol":"CZK","native":"K\u010d","thousands_sep":"\u00a0","decimal_sep":",","symbol_left":false,"space_between":true,"exp":2,"min_amount":"2315","max_amount":"23156503"},"DKK":{"code":"DKK","title":"Danish Krone","symbol":"DKK","native":"kr","thousands_sep":"","decimal_sep":",","symbol_left":false,"space_between":true,"exp":2,"min_amount":"676","max_amount":"6762220"},"DOP":{"code":"DOP","title":"Dominican Peso","symbol":"DOP","native":"$","thousands_sep":",","decimal_sep":".","symbol_left":true,"space_between":false,"exp":2,"min_amount":"5284","max_amount":"52847106"},"DZD":{"code":"DZD","title":"Algerian Dinar","symbol":"DZD","native":"\u062f.\u062c.\u200f","thousands_sep":",","decimal_sep":".","symbol_left":true,"space_between":true,"exp":2,"min_amount":"12001","max_amount":"120015007"},"EGP":{"code":"EGP","title":"Egyptian Pound","symbol":"EGP","native":"\u062c.\u0645.\u200f","thousands_sep":",","decimal_sep":".","symbol_left":true,"space_between":true,"exp":2,"min_amount":"1613","max_amount":"16131899"},"EUR":{"code":"EUR","title":"Euro","symbol":"\u20ac","native":"\u20ac","thousands_sep":"\u00a0","decimal_sep":",","symbol_left":false,"space_between":true,"exp":2,"min_amount":"90","max_amount":"904920"},"GBP":{"code":"GBP","title":"British Pound","symbol":"\u00a3","native":"\u00a3","thousands_sep":",","decimal_sep":".","symbol_left":true,"space_between":false,"exp":2,"min_amount":"77","max_amount":"775065"},"GEL":{"code":"GEL","title":"Georgian Lari","symbol":"GEL","native":"GEL","thousands_sep":"\u00a0","decimal_sep":",","symbol_left":false,"space_between":true,"exp":2,"min_amount":"296","max_amount":"2965017"},"GTQ":{"code":"GTQ","title":"Guatemalan Quetzal","symbol":"GTQ","native":"Q","thousands_sep":",","decimal_sep":".","symbol_left":true,"space_between":false,"exp":2,"min_amount":"770","max_amount":"7706297"},"HKD":{"code":"HKD","title":"Hong Kong Dollar","symbol":"HK$","native":"$","thousands_sep":",","decimal_sep":".","symbol_left":true,"space_between":false,"exp":2,"min_amount":"782","max_amount":"7826350"},"HNL":{"code":"HNL","title":"Honduran Lempira","symbol":"HNL","native":"L","thousands_sep":",","decimal_sep":".","symbol_left":true,"space_between":true,"exp":2,"min_amount":"2473","max_amount":"24730090"},"HRK":{"code":"HRK","title":"Croatian Kuna","symbol":"HRK","native":"kn","thousands_sep":".","decimal_sep":",","symbol_left":false,"space_between":true,"exp":2,"min_amount":"673","max_amount":"6730821"},"HUF":{"code":"HUF","title":"Hungarian Forint","symbol":"HUF","native":"Ft","thousands_sep":"\u00a0","decimal_sep":",","symbol_left":false,"space_between":true,"exp":2,"min_amount":"30269","max_amount":"302699746"},"IDR":{"code":"IDR","title":"Indonesian Rupiah","symbol":"IDR","native":"Rp","thousands_sep":".","decimal_sep":",","symbol_left":true,"space_between":false,"exp":2,"min_amount":"1405950","max_amount":"14059500000"},"ILS":{"code":"ILS","title":"Israeli New Sheqel","symbol":"\u20aa","native":"\u20aa","thousands_sep":",","decimal_sep":".","symbol_left":true,"space_between":true,"exp":2,"min_amount":"347","max_amount":"3472250"},"INR":{"code":"INR","title":"Indian Rupee","symbol":"\u20b9","native":"\u20b9","thousands_sep":",","decimal_sep":".","symbol_left":true,"space_between":false,"exp":2,"min_amount":"7164","max_amount":"71642499"},"ISK":{"code":"ISK","title":"Icelandic Kr\u00f3na","symbol":"ISK","native":"kr","thousands_sep":".","decimal_sep":",","symbol_left":false,"space_between":true,"exp":0,"min_amount":"122","max_amount":"1229899"},"JMD":{"code":"JMD","title":"Jamaican Dollar","symbol":"JMD","native":"$","thousands_sep":",","decimal_sep":".","symbol_left":true,"space_between":false,"exp":2,"min_amount":"14055","max_amount":"140559360"},"JPY":{"code":"JPY","title":"Japanese Yen","symbol":"\u00a5","native":"\uffe5","thousands_sep":",","decimal_sep":".","symbol_left":true,"space_between":false,"exp":0,"min_amount":"108","max_amount":"1087579"},"KES":{"code":"KES","title":"Kenyan Shilling","symbol":"KES","native":"Ksh","thousands_sep":",","decimal_sep":".","symbol_left":true,"space_between":false,"exp":2,"min_amount":"10195","max_amount":"101950880"},"KGS":{"code":"KGS","title":"Kyrgyzstani Som","symbol":"KGS","native":"KGS","thousands_sep":"\u00a0","decimal_sep":"-","symbol_left":false,"space_between":true,"exp":2,"min_amount":"6985","max_amount":"69850414"},"KRW":{"code":"KRW","title":"South Korean Won","symbol":"\u20a9","native":"\u20a9","thousands_sep":",","decimal_sep":".","symbol_left":true,"space_between":false,"exp":0,"min_amount":"1163","max_amount":"11639302"},"KZT":{"code":"KZT","title":"Kazakhstani Tenge","symbol":"KZT","native":"\u20b8","thousands_sep":"\u00a0","decimal_sep":"-","symbol_left":true,"space_between":false,"exp":2,"min_amount":"38809","max_amount":"388092580"},"LBP":{"code":"LBP","title":"Lebanese Pound","symbol":"LBP","native":"\u0644.\u0644.\u200f","thousands_sep":",","decimal_sep":".","symbol_left":true,"space_between":true,"exp":2,"min_amount":"151200","max_amount":"1512000096"},"LKR":{"code":"LKR","title":"Sri Lankan Rupee","symbol":"LKR","native":"\u0dbb\u0dd4.","thousands_sep":",","decimal_sep":".","symbol_left":true,"space_between":true,"exp":2,"min_amount":"18023","max_amount":"180231820"},"MAD":{"code":"MAD","title":"Moroccan Dirham","symbol":"MAD","native":"\u062f.\u0645.\u200f","thousands_sep":",","decimal_sep":".","symbol_left":true,"space_between":true,"exp":2,"min_amount":"965","max_amount":"9652502"},"MDL":{"code":"MDL","title":"Moldovan Leu","symbol":"MDL","native":"MDL","thousands_sep":",","decimal_sep":".","symbol_left":false,"space_between":true,"exp":2,"min_amount":"1756","max_amount":"17562714"},"MNT":{"code":"MNT","title":"Mongolian T\u00f6gr\u00f6g","symbol":"MNT","native":"MNT","thousands_sep":"\u00a0","decimal_sep":",","symbol_left":true,"space_between":false,"exp":2,"min_amount":"270611","max_amount":"2706118534"},"MUR":{"code":"MUR","title":"Mauritian Rupee","symbol":"MUR","native":"MUR","thousands_sep":",","decimal_sep":".","symbol_left":true,"space_between":false,"exp":2,"min_amount":"3659","max_amount":"36591433"},"MVR":{"code":"MVR","title":"Maldivian Rufiyaa","symbol":"MVR","native":"MVR","thousands_sep":",","decimal_sep":".","symbol_left":false,"space_between":true,"exp":2,"min_amount":"1535","max_amount":"15350392"},"MXN":{"code":"MXN","title":"Mexican Peso","symbol":"MX$","native":"$","thousands_sep":",","decimal_sep":".","symbol_left":true,"space_between":false,"exp":2,"min_amount":"1921","max_amount":"19214197"},"MYR":{"code":"MYR","title":"Malaysian Ringgit","symbol":"MYR","native":"RM","thousands_sep":",","decimal_sep":".","symbol_left":true,"space_between":false,"exp":2,"min_amount":"415","max_amount":"4152993"},"MZN":{"code":"MZN","title":"Mozambican Metical","symbol":"MZN","native":"MTn","thousands_sep":",","decimal_sep":".","symbol_left":true,"space_between":false,"exp":2,"min_amount":"6335","max_amount":"63350421"},"NGN":{"code":"NGN","title":"Nigerian Naira","symbol":"NGN","native":"\u20a6","thousands_sep":",","decimal_sep":".","symbol_left":true,"space_between":false,"exp":2,"min_amount":"36151","max_amount":"361513701"},"NIO":{"code":"NIO","title":"Nicaraguan C\u00f3rdoba","symbol":"NIO","native":"C$","thousands_sep":",","decimal_sep":".","symbol_left":true,"space_between":true,"exp":2,"min_amount":"3394","max_amount":"33949827"},"NOK":{"code":"NOK","title":"Norwegian Krone","symbol":"NOK","native":"kr","thousands_sep":"\u00a0","decimal_sep":",","symbol_left":true,"space_between":true,"exp":2,"min_amount":"907","max_amount":"9077015"},"NPR":{"code":"NPR","title":"Nepalese Rupee","symbol":"NPR","native":"\u0928\u0947\u0930\u0942","thousands_sep":",","decimal_sep":".","symbol_left":true,"space_between":false,"exp":2,"min_amount":"11490","max_amount":"114900650"},"NZD":{"code":"NZD","title":"New Zealand Dollar","symbol":"NZ$","native":"$","thousands_sep":",","decimal_sep":".","symbol_left":true,"space_between":false,"exp":2,"min_amount":"156","max_amount":"1561570"},"PAB":{"code":"PAB","title":"Panamanian Balboa","symbol":"PAB","native":"B\/.","thousands_sep":",","decimal_sep":".","symbol_left":true,"space_between":true,"exp":2,"min_amount":"100","max_amount":"1000162"},"PEN":{"code":"PEN","title":"Peruvian Nuevo Sol","symbol":"PEN","native":"S\/.","thousands_sep":",","decimal_sep":".","symbol_left":true,"space_between":true,"exp":2,"min_amount":"337","max_amount":"3370293"},"PHP":{"code":"PHP","title":"Philippine Peso","symbol":"PHP","native":"\u20b1","thousands_sep":",","decimal_sep":".","symbol_left":true,"space_between":false,"exp":2,"min_amount":"5058","max_amount":"50580162"},"PKR":{"code":"PKR","title":"Pakistani Rupee","symbol":"PKR","native":"\u20a8","thousands_sep":",","decimal_sep":".","symbol_left":true,"space_between":false,"exp":2,"min_amount":"15549","max_amount":"155498853"},"PLN":{"code":"PLN","title":"Polish Z\u0142oty","symbol":"PLN","native":"z\u0142","thousands_sep":"\u00a0","decimal_sep":",","symbol_left":false,"space_between":true,"exp":2,"min_amount":"386","max_amount":"3866750"},"PYG":{"code":"PYG","title":"Paraguayan Guaran\u00ed","symbol":"PYG","native":"\u20b2","thousands_sep":".","decimal_sep":",","symbol_left":true,"space_between":true,"exp":0,"min_amount":"6446","max_amount":"64460359"},"QAR":{"code":"QAR","title":"Qatari Riyal","symbol":"QAR","native":"\u0631.\u0642.\u200f","thousands_sep":",","decimal_sep":".","symbol_left":true,"space_between":true,"exp":2,"min_amount":"364","max_amount":"3640962"},"RON":{"code":"RON","title":"Romanian Leu","symbol":"RON","native":"RON","thousands_sep":".","decimal_sep":",","symbol_left":false,"space_between":true,"exp":2,"min_amount":"431","max_amount":"4314800"},"RSD":{"code":"RSD","title":"Serbian Dinar","symbol":"RSD","native":"\u0434\u0438\u043d.","thousands_sep":".","decimal_sep":",","symbol_left":false,"space_between":true,"exp":2,"min_amount":"10627","max_amount":"106270698"},"RUB":{"code":"RUB","title":"Russian Ruble","symbol":"RUB","native":"\u0440\u0443\u0431.","thousands_sep":"\u00a0","decimal_sep":",","symbol_left":false,"space_between":true,"exp":2,"min_amount":"6374","max_amount":"63742030"},"SAR":{"code":"SAR","title":"Saudi Riyal","symbol":"SAR","native":"\u0631.\u0633.\u200f","thousands_sep":",","decimal_sep":".","symbol_left":true,"space_between":true,"exp":2,"min_amount":"375","max_amount":"3750249"},"SEK":{"code":"SEK","title":"Swedish Krona","symbol":"SEK","native":"kr","thousands_sep":".","decimal_sep":",","symbol_left":false,"space_between":true,"exp":2,"min_amount":"963","max_amount":"9634530"},"SGD":{"code":"SGD","title":"Singapore Dollar","symbol":"SGD","native":"$","thousands_sep":",","decimal_sep":".","symbol_left":true,"space_between":false,"exp":2,"min_amount":"136","max_amount":"1360290"},"THB":{"code":"THB","title":"Thai Baht","symbol":"\u0e3f","native":"\u0e3f","thousands_sep":",","decimal_sep":".","symbol_left":true,"space_between":false,"exp":2,"min_amount":"3026","max_amount":"30269819"},"TJS":{"code":"TJS","title":"Tajikistani Somoni","symbol":"TJS","native":"TJS","thousands_sep":"\u00a0","decimal_sep":";","symbol_left":false,"space_between":true,"exp":2,"min_amount":"969","max_amount":"9699549"},"TRY":{"code":"TRY","title":"Turkish Lira","symbol":"TRY","native":"TL","thousands_sep":".","decimal_sep":",","symbol_left":false,"space_between":true,"exp":2,"min_amount":"573","max_amount":"5739896"},"TTD":{"code":"TTD","title":"Trinidad and Tobago Dollar","symbol":"TTD","native":"$","thousands_sep":",","decimal_sep":".","symbol_left":true,"space_between":false,"exp":2,"min_amount":"678","max_amount":"6781378"},"TWD":{"code":"TWD","title":"New Taiwan Dollar","symbol":"NT$","native":"NT$","thousands_sep":",","decimal_sep":".","symbol_left":true,"space_between":false,"exp":2,"min_amount":"3049","max_amount":"30499503"},"TZS":{"code":"TZS","title":"Tanzanian Shilling","symbol":"TZS","native":"TSh","thousands_sep":",","decimal_sep":".","symbol_left":true,"space_between":false,"exp":2,"min_amount":"230840","max_amount":"2308402799"},"UAH":{"code":"UAH","title":"Ukrainian Hryvnia","symbol":"UAH","native":"\u20b4","thousands_sep":"\u00a0","decimal_sep":",","symbol_left":false,"space_between":false,"exp":2,"min_amount":"2419","max_amount":"24197257"},"UGX":{"code":"UGX","title":"Ugandan Shilling","symbol":"UGX","native":"USh","thousands_sep":",","decimal_sep":".","symbol_left":true,"space_between":false,"exp":0,"min_amount":"3690","max_amount":"36905948"},"USD":{"code":"USD","title":"United States Dollar","symbol":"$","native":"$","thousands_sep":",","decimal_sep":".","symbol_left":true,"space_between":false,"exp":2,"min_amount":"100","max_amount":1000000},"UYU":{"code":"UYU","title":"Uruguayan Peso","symbol":"UYU","native":"$","thousands_sep":".","decimal_sep":",","symbol_left":true,"space_between":true,"exp":2,"min_amount":"3759","max_amount":"37590317"},"UZS":{"code":"UZS","title":"Uzbekistani Som","symbol":"UZS","native":"UZS","thousands_sep":"\u00a0","decimal_sep":",","symbol_left":false,"space_between":true,"exp":2,"min_amount":"949499","max_amount":"9494999743"},"VND":{"code":"VND","title":"Vietnamese \u0110\u1ed3ng","symbol":"\u20ab","native":"\u20ab","thousands_sep":".","decimal_sep":",","symbol_left":false,"space_between":true,"exp":0,"min_amount":"23208","max_amount":"232085000"},"YER":{"code":"YER","title":"Yemeni Rial","symbol":"YER","native":"\u0631.\u064a.\u200f","thousands_sep":",","decimal_sep":".","symbol_left":true,"space_between":true,"exp":2,"min_amount":"25034","max_amount":"250349976"},"ZAR":{"code":"ZAR","title":"South African Rand","symbol":"ZAR","native":"R","thousands_sep":",","decimal_sep":".","symbol_left":true,"space_between":true,"exp":2,"min_amount":"1467","max_amount":"14673050"}}